{
    "video_id": "3t2fSV2DSVg",
    "newspaper": "lastampa",
    "title": "\u00c8 il giorno del caldo record, nel pomeriggio si tocca il picco: 37 gradi percepiti",
    "channel": "La Stampa",
    "published_at": "2026-05-27T12:29:28Z",
    "description": "Arriver\u00e0 a 37 gradi la temperatura massima percepita. \u00c8 il giorno del caldo record in questa che sembra gi\u00e0 piena estate. L\u2019ondata di calore che ha invaso tutta l\u2019Europa da inizio settimana ha portato su Torino e il Piemonte temperature record. L\u2019alta pressione che dal Marocco ha investito la penisola iberica e poi tutto il continente toccher\u00e0 il picco nel pomeriggio. Per far fronte all\u2019emergenza, da oggi aprono i 19 centri climatizzati che il Comune ha messo a disposizione delle persone pi\u00f9 fragili.\n\nIl racconto integrale di Marco Accossato \u00e8 su La Stampa - Torino\n\n#caldo #Torino #LaStampa",
    "tags": "",
    "view_count": 7756,
    "like_count": 42,
    "comment_count": 2
}