{
  "video_id": "a8wzgiJ8C9o",
  "newspaper": "il_gazzettino",
  "title": "Faida tra bande di tunisini a colpi di machete, 5 Sakka in carcere per tentato omicidio e lesioni",
  "channel": "Il Gazzettino",
  "published_at": "2026-05-20T17:15:32Z",
  "description": "Dopo l'episodio choc della faida tra bande di tunisini a colpi di machete nel centro storico di Venezia, dove sabato notte alle Zattere sono stati feriti due componenti della famiglia Mallat, un 32enne e un 22enne, ora scattano gli arresti. Il blitz di polizia e carabinieri è in corso dalle prime ore di questa mattina, mercoledì 20 maggio, a seguito delle indagini coordinate dalla Procura della Repubblica lagunare\n\nPer ulteriori approfondimenti: https://l-nk.it/dkH8A3",
  "tags": "gazzettino, il gazzettino",
  "view_count": 19117,
  "like_count": 39,
  "comment_count": 2,
  "topic": "crime, law and justice"
}