{
  "video_id": "FYKewQOzPrI",
  "newspaper": "il_gazzettino",
  "title": "Biennale, Salvini accolto nel padiglione russo con un canto siberiano",
  "channel": "Il Gazzettino",
  "published_at": "2026-05-08T21:03:30Z",
  "description": "Un canto siberiano: così il padiglione russo ha accolto il ministro delle Infrastrutture e dei Trasporti, Matteo Salvini, arrivato oggi, venerdì 8 maggio, alla Biennale (video di Alda Vanzan) \n\nPer approfondimenti: https://l-nk.it/6ibA9T",
  "tags": "gazzettino, il gazzettino",
  "view_count": 8071,
  "like_count": 65,
  "comment_count": 39,
  "topic": "arts, culture, entertainment and media"
}