{
  "video_id": "OjpQt5jLMR0",
  "newspaper": "lastampa",
  "title": "Zaia ricorda Petrini: \"Mi dicevano 'Fai attenzione perché è un uomo di sinistra'\"",
  "channel": "La Stampa",
  "published_at": "2026-05-24T14:12:50Z",
  "description": "«Fai attenzione, perché è un uomo di sinistra», mi dicevano tutti prima che incontrassi Carlin Petrini. Io trovai una persona illuminata, unica».\n\nLuca Zaia ricorda ancora il suo primo incontro con il fondatore di Slow Food. «Era il 2008 e un giornale organizzò un faccia a faccia tra il ministro leghista e il comunista Carlin Petrini. Doveva essere uno scontro ideologico, invece il giornalista rimase deluso: sugli Ogm, sulla difesa delle produzioni locali, sulla sostenibilità e sulla tutela dei contadini eravamo completamente d’accordo».\n\nIl racconto integrale di Francesco Moscatelli è su La Stampa\n\n#LaStampa",
  "tags": "",
  "view_count": 26042,
  "like_count": 63,
  "comment_count": 2,
  "topic": "politics and government"
}