{
  "video_id": "dS-yHRgujPM",
  "newspaper": "repubblica",
  "title": "Pedro Almodóvar: \"La mia vita è diventata i film che faccio”",
  "channel": "La Repubblica",
  "published_at": "2026-05-23T18:00:37Z",
  "description": "“La ragione di un film è sempre misteriosa”, dice Pedro Almodóvar. A 76 anni, il regista torna al Festival di Cannes con “Amarga Navidad”, uno dei film più personali della sua carriera, in sala dal 21 maggio per Warner. Il film racconta il lutto e il confine fragile tra vita e finzione: Elsa, regista segnata dalla morte della madre, cerca rifugio nel lavoro, mentre Raúl, scrittore in crisi, trasforma quella vicenda in un film.\n\nAlmodóvar dice di non aver vissuto una crisi creativa simile, ma riconosce nel protagonista qualcosa di sé: “Per me fare cinema è una vera e propria dipendenza”. E aggiunge che alcuni momenti del film nascono dalla sua vita e dal dolore di persone molto care.\n\nL’intervista completa di Arianna Finos su Repubblica\n#rep",
  "tags": "",
  "view_count": 8405,
  "like_count": 36,
  "comment_count": 4,
  "topic": "arts, culture, entertainment and media"
}